pyiqa/__init__.py
pyiqa/api_helpers.py
pyiqa/default_dataset_configs.yml
pyiqa/default_model_configs.py
pyiqa/pyiqa_cmd.py
pyiqa/test.py
pyiqa/train.py
pyiqa/train_nsplits.py
pyiqa/version.py
pyiqa/archs/__init__.py
pyiqa/archs/ahiq_arch.py
pyiqa/archs/arch_util.py
pyiqa/archs/arniqa_arch.py
pyiqa/archs/brisque_arch.py
pyiqa/archs/ckdn_arch.py
pyiqa/archs/class_mapping.json
pyiqa/archs/clip_model.py
pyiqa/archs/clipiqa_arch.py
pyiqa/archs/clipscore_arch.py
pyiqa/archs/cnniqa_arch.py
pyiqa/archs/compare2score_arch.py
pyiqa/archs/constants.py
pyiqa/archs/dbcnn_arch.py
pyiqa/archs/deepdc_arch.py
pyiqa/archs/dists_arch.py
pyiqa/archs/entropy_arch.py
pyiqa/archs/fid_arch.py
pyiqa/archs/fsim_arch.py
pyiqa/archs/func_util.py
pyiqa/archs/gmsd_arch.py
pyiqa/archs/hypernet_arch.py
pyiqa/archs/inception.py
pyiqa/archs/inceptionscore_arch.py
pyiqa/archs/interpolate_compat_tensorflow.py
pyiqa/archs/iqt_arch.py
pyiqa/archs/laion_aes_arch.py
pyiqa/archs/liqe_arch.py
pyiqa/archs/lpips_arch.py
pyiqa/archs/mad_arch.py
pyiqa/archs/maniqa_arch.py
pyiqa/archs/maniqa_swin.py
pyiqa/archs/msswd_arch.py
pyiqa/archs/musiq_arch.py
pyiqa/archs/nima_arch.py
pyiqa/archs/niqe_arch.py
pyiqa/archs/nlpd_arch.py
pyiqa/archs/nrqm_arch.py
pyiqa/archs/paq2piq_arch.py
pyiqa/archs/pieapp_arch.py
pyiqa/archs/piqe_arch.py
pyiqa/archs/psnr_arch.py
pyiqa/archs/qalign_arch.py
pyiqa/archs/qualiclip_arch.py
pyiqa/archs/ssim_arch.py
pyiqa/archs/stlpips_arch.py
pyiqa/archs/topiq_arch.py
pyiqa/archs/topiq_swin.py
pyiqa/archs/tres_arch.py
pyiqa/archs/unique_arch.py
pyiqa/archs/uranker_arch.py
pyiqa/archs/vif_arch.py
pyiqa/archs/vsi_arch.py
pyiqa/archs/wadiqam_arch.py
pyiqa/data/__init__.py
pyiqa/data/ava_dataset.py
pyiqa/data/bapps_dataset.py
pyiqa/data/base_iqa_dataset.py
pyiqa/data/data_sampler.py
pyiqa/data/data_util.py
pyiqa/data/dataset_api.py
pyiqa/data/general_fr_dataset.py
pyiqa/data/general_nr_dataset.py
pyiqa/data/livechallenge_dataset.py
pyiqa/data/multiscale_trans_util.py
pyiqa/data/pieapp_dataset.py
pyiqa-0.1.14.1.dist-info/LICENSE
pyiqa-0.1.14.1.dist-info/LICENSE-S-Lab
pyiqa-0.1.14.1.dist-info/METADATA
pyiqa-0.1.14.1.dist-info/WHEEL
pyiqa-0.1.14.1.dist-info/entry_points.txt
pyiqa-0.1.14.1.dist-info/top_level.txt
pyiqa-0.1.14.1.dist-info/RECORD
