Metadata-Version: 2.2
Name: pyiqa
Version: 0.1.14.1
Summary: PyTorch Toolbox for Image Quality Assessment
Home-page: https://github.com/chaofengc/IQA-PyTorch
Author: Chaofeng Chen
Author-email: chaofenghust@gmail.com
Keywords: image quality assessment,pytorch
Classifier: Development Status :: 3 - Alpha
Classifier: Intended Audience :: Science/Research
Classifier: License :: OSI Approved :: Apache Software License
Classifier: Operating System :: OS Independent
Classifier: Programming Language :: Python :: 3.6
Classifier: Programming Language :: Python :: 3.7
Classifier: Programming Language :: Python :: 3.8
Classifier: Topic :: Scientific/Engineering
Classifier: Topic :: Scientific/Engineering :: Image Processing
Requires-Python: >=3.6
License-File: LICENSE
License-File: LICENSE-S-Lab
Requires-Dist: accelerate<=1.1.0
Requires-Dist: addict
Requires-Dist: datasets
Requires-Dist: bitsandbytes; sys_platform != "darwin"
Requires-Dist: einops
Requires-Dist: facexlib
Requires-Dist: future
Requires-Dist: icecream
Requires-Dist: lmdb
Requires-Dist: numpy
Requires-Dist: openai-clip
Requires-Dist: opencv-python-headless
Requires-Dist: pandas
Requires-Dist: Pillow
Requires-Dist: pre-commit
Requires-Dist: pytest
Requires-Dist: pyyaml
Requires-Dist: requests
Requires-Dist: ruff
Requires-Dist: scikit-image
Requires-Dist: scipy
Requires-Dist: sentencepiece
Requires-Dist: tensorboard
Requires-Dist: timm>=0.8
Requires-Dist: torch>=1.12
Requires-Dist: torchvision>=0.13
Requires-Dist: tqdm
Requires-Dist: transformers==4.37.2
Requires-Dist: yapf
Dynamic: author
Dynamic: author-email
Dynamic: classifier
Dynamic: description
Dynamic: description-content-type
Dynamic: home-page
Dynamic: keywords
Dynamic: requires-dist
Dynamic: requires-python
Dynamic: summary
